metalparser/__init__.py
metalparser/darklyrics.py
metalparser/common/__init__.py
metalparser/common/exceptions.py
metalparser/common/logger.py
metalparser/common/scraping.py
metalparser/common/resources/__init__.py
metalparser/common/resources/user_agents.json
metalparser/libs/__init__.py
metalparser/libs/darklyrics_utils.py
metalparser-0.6.9b1.dist-info/LICENSE
metalparser-0.6.9b1.dist-info/METADATA
metalparser-0.6.9b1.dist-info/WHEEL
metalparser-0.6.9b1.dist-info/top_level.txt
metalparser-0.6.9b1.dist-info/RECORD
