Metadata-Version: 2.1
Name: metalparser
Version: 0.6.9b1
Summary: Python library for heavy metal song lyrics, albums, song titles and other info.
Home-page: https://github.com/lucone83/metal-parser
Author: Luca Ballore
Author-email: luca@ballore.eu
License: MIT
Project-URL: Bug Reports, https://github.com/lucone83/metal-parser/issues
Project-URL: Disclaimer, https://github.com/lucone83/metal-parser/blob/master/DISCLAIMER.md
Project-URL: Docs, https://metalparser.readthedocs.io/
Project-URL: Funding, https://donate.pypi.org
Project-URL: Source, https://github.com/lucone83/metal-parser
Keywords: heavy metal darklyrics lyrics song api
Platform: UNKNOWN
Classifier: Development Status :: 4 - Beta
Classifier: Intended Audience :: Developers
Classifier: Topic :: Software Development :: Build Tools
Classifier: License :: OSI Approved :: MIT License
Classifier: Programming Language :: Python :: 3.4
Classifier: Programming Language :: Python :: 3.5
Classifier: Programming Language :: Python :: 3.6
Classifier: Programming Language :: Python :: 3.7
Classifier: Programming Language :: Python :: 3.8
Requires-Python: >=3.4.*, <=3.8
Requires-Dist: beautifulsoup4
Requires-Dist: ratelimit
Requires-Dist: requests
Requires-Dist: requests-cache
